aboto3/__init__.py
aboto3/aio_client.py
aboto3/aio_page_iterator.py
aboto3/aio_paginator.py
aboto3-0.1.2.dist-info/LICENSE
aboto3-0.1.2.dist-info/METADATA
aboto3-0.1.2.dist-info/WHEEL
aboto3-0.1.2.dist-info/top_level.txt
aboto3-0.1.2.dist-info/RECORD
